README.md
setup.py
pylnd/__init__.py
pylnd/abstraction.py
pylnd/utils.py
pylnd.egg-info/PKG-INFO
pylnd.egg-info/SOURCES.txt
pylnd.egg-info/dependency_links.txt
pylnd.egg-info/requires.txt
pylnd.egg-info/top_level.txt
pylnd/rest/__init__.py