Metadata-Version: 2.1
Name: pylnd
Version: 0.2.3
Summary: Python client for Lightning Network Deamon
Home-page: https://github.com/smadici-labs/pylnd
Author: Gabriel Smadi
Author-email: gabriel@labs.smadi.ci
License: MIT
Platform: UNKNOWN
Classifier: Development Status :: 3 - Alpha
Classifier: Programming Language :: Python :: 3.6
Classifier: License :: OSI Approved :: MIT License
Classifier: Operating System :: OS Independent
Provides-Extra: docs
Provides-Extra: dev
